vcc_py/__init__.py
vcc_py/__main__.py
vcc_py/bh.py
vcc_py/commands.py
vcc_py/config.py
vcc_py/constants.py
vcc_py/crypt.py
vcc_py/plugin.py
vcc_py/pretty.py
vcc_py/readconf.py
vcc_py/sock.py
vcc_py/vcc.py
vcc_py/plugins/__init__.py
vcc_py/plugins/ban.py
vcc_py/plugins/beep.py
vcc_py/plugins/cqd.py
vcc_py/plugins/m4.py
vcc_py/plugins/raw.py
vcc_py/plugins/vcr.py
vcc_py-0.3.17.dist-info/LICENSE
vcc_py-0.3.17.dist-info/METADATA
vcc_py-0.3.17.dist-info/WHEEL
vcc_py-0.3.17.dist-info/entry_points.txt
vcc_py-0.3.17.dist-info/top_level.txt
vcc_py-0.3.17.dist-info/RECORD
