Metadata-Version: 2.1
Name: vcc-py
Version: 0.3.17
Summary: the python version of vcc
Maintainer: 3swordman
Maintainer-email: yyuxiaoran@gmail.com
Requires-Python: >=3.10
License-File: LICENSE
Requires-Dist: importlib-metadata
Requires-Dist: pycryptdome
Requires-Dist: prompt-toolkit
